arf/ACJA2Client.py
arf/Tile.py
arf/TileConstants.py
airbornerf_aviation_sdk-2.1.0.dist-info/METADATA
airbornerf_aviation_sdk-2.1.0.dist-info/WHEEL
airbornerf_aviation_sdk-2.1.0.dist-info/top_level.txt
airbornerf_aviation_sdk-2.1.0.dist-info/RECORD
