Metadata-Version: 2.1
Name: airbornerf-aviation-sdk
Version: 2.1.0
Summary: AirborneRF Aviation SDK
Home-page: https://www.airbornerf.com/
Author: Thomas Wana
Author-email: support@airbornerf.com
License: Proprietary
Requires-Dist: requests
Requires-Dist: numpy
